timone/__init__.py
timone/api.py
timone/auth.py
timone/controller.py
timone/errors.py
timone/storage.py
timone/wsgi.py
timone-0.4.0.dist-info/LICENSE
timone-0.4.0.dist-info/METADATA
timone-0.4.0.dist-info/WHEEL
timone-0.4.0.dist-info/top_level.txt
timone-0.4.0.dist-info/RECORD
