Metadata-Version: 2.1
Name: timone
Version: 0.4.0
Summary: A lightweight object router to store Git LFS objects on different storage backend.
Home-page: https://github.com/gstracquadanio/timone.git
Author: Giovanni Stracquadanio
Author-email: dr.stracquadanio@gmail.com
License: MIT
Platform: UNKNOWN
Classifier: License :: OSI Approved :: MIT License
Classifier: Programming Language :: Python :: 3
Classifier: Programming Language :: Python :: 3.7
Classifier: Programming Language :: Python :: 3.8
Requires-Dist: python-dotenv (>=0.10.3)
Requires-Dist: falcon (>=2.0.0)
Requires-Dist: boto3 (>=1.10)
Requires-Dist: PyJWT (>=1.7.1)
